{
  "TITLE" : "专项：冬奥会考点预测题",
  "MODULEARRS" : [
    {
      "ModuleTitile" : "模块1: 单选题部分",
      "ModuleContentArr" : [
        {
          "OptionB" : "B.国家速滑馆是全球首个采用二氧化碳跨临界直冷制冰技术的冬奥速滑场馆",
          "OptionA" : "A.国家速滑馆是北京冬奥会赛事唯一新建雪.上竞赛场馆",
          "TopicContent" : "1.2022年1月4日，习近平来到国家速滑馆考察。关于该馆，下列说法不正确的是( ),",
          "AnswerArr" : [
            "A"
          ],
          "IsMultipleChoice" : false,
          "AnswerContent" : "[关注公众号人才考试答案] A。A项错误，国家速滑馆又称“冰丝带”，是本届赛事唯一新建冰上竞赛场馆。B项正确，国家速滑馆是全球首个采用二氧化碳跨临界直冷制冰技术的冬奥速滑场馆。C项正确，国家速滑馆将承担速度滑冰项目的比赛，共产生14块金牌，是冬奥会产生金牌数量最多的单个场馆。D项正确，国家速滑馆拥有世界跨度最大的单层双向正交马鞍形索网屋面。",
          "OptionD" : "D.国家速滑馆拥有世界跨度最大的单层双向正交马鞍形索网屋面",
          "OptionC" : "C.国家速滑馆是冬奥会产生金牌数量最多的单个场馆"
        },
        {
          "OptionB" : "B.绿色、共享、开放、廉洁",
          "OptionA" : "A.环保、公平、竞争、和谐",
          "TopicContent" : "2.办好2022年北京冬奥会，是我国对国际奥林匹克大家庭的庄严承诺，也是实施京津冀协同发展战略的重要举措。我国2022年北京冬奥会的办奥理念是()",
          "AnswerArr" : [
            "B"
          ],
          "IsMultipleChoice" : false,
          "AnswerContent" : "[答案]关注公众号人才考试B。解析:习近平指出，要全面落实绿色、共享开放、廉洁的办奧理念，充分考虑场馆的可持续利用问题，高标准、高质量完成各项筹办任务。关注公众号人才考试",
          "OptionD" : "D.共享、友好、竞争、绿色",
          "OptionC" : "C.生态、温暖、公平、实用"
        },
        {
          "OptionB" : "B.我国第一位夺得冬奥会金牌的运动员是王檬",
          "OptionA" : "A.北京成为全球首个获过冬、夏两季奥运会举办权的城市",
          "TopicContent" : "3.下列关于冬奥会的说法中正确的是()。",
          "AnswerArr" : [
            "A"
          ],
          "IsMultipleChoice" : false,
          "AnswerContent" : "[答案] A。A项正确，北京是第一个举办夏奥会又举办冬奥会的城市。B项错误，2002 年盐湖城冬季奥运会.上，杨扬成为中国冬季奥运史上第一一个夺得金牌的选手。C项错误，第一届冬季奥林匹克运动会于1924年1月25日在法国的夏蒙尼举行，因此，第一个举办冬奥会的城市是法国的夏蒙尼。D项错误，冰壶属于竞技类项且，而非比速度。关注公众号人才考试",
          "OptionD" : "D.冬奥会项目分为竞速类和技巧类，其中冰壶属于竞速类项目",
          "OptionC" : "C.第一届冬奥会在加拿大温哥华举办."
        },
        {
          "OptionB" : "B.石灰岩",
          "OptionA" : "A.花岗岩",
          "TopicContent" : "4.在冬奥会的赛场上，冰壶项目深受大家喜爱。作为冰上投掷项目，冰壶在制作过程中，对原石材料有着特殊的要求。首先需要石材足够坚硬，其次要求在低温条件下不能被撞裂。那么最适宜的岩石是()。",
          "AnswerArr" : [
            "A"
          ],
          "IsMultipleChoice" : false,
          "AnswerContent" : "[答案] A。解析:最常见的坚硬岩石是花岗岩，而在制作和使用冰壶的过程中，大家发现当花岗岩中的石英含量较低时，冰壶壶体在低温撞击时才不容易破裂。关注公众号人才考试[拓展]冬奥会级别冰壶原石，采自于苏格兰的一个小岛克里格岛，该小岛也被称为“冰壶圣地”。由这个小岛上开采的花岗岩制作而成的冰壶是世界.上最优质的冰壶。关注公众号人才考试",
          "OptionD" : "D.石英岩.",
          "OptionC" : "C.大理岩"
        },
        {
          "OptionB" : "B.跳台滑雪射击",
          "OptionA" : "A.射击跳台滑雪",
          "TopicContent" : "5.在冬奥会雪上项目中，冬季两项和北欧两项的名字非常相像，不免令人有些分不清。从比赛内容上看，冬季两项与北欧两项都涉及越野滑雪，但前者多了()项目，后者则多了()项目。",
          "AnswerArr" : [
            "A"
          ],
          "IsMultipleChoice" : false,
          "AnswerContent" : "[答案] A。冬季两项中，进行越野滑雪和射击比赛，要求运动员身着越野滑雪装备，背负专用小口径步枪，每滑行一段距离进行一次射击，最先到达终点者优胜。北欧两项则是将跳台滑雪与越野滑雪结合起来。运动员要先进行跳台滑雪比赛，再进行越野滑雪比赛。关注公众号人才考试",
          "OptionD" : "D.雪上田径单板滑雪.",
          "OptionC" : "C.单板滑雪雪上田径"
        },
        {
          "OptionB" : "B.札幌",
          "OptionA" : "A.东京",
          "TopicContent" : "6.2015年7月31日，北京携手张家口获得2022年冬奥会举办权。这是中国历史.上第一次举办冬季奥运会。亚洲第一个主办冬奧会的城市是( ) 。",
          "AnswerArr" : [
            "B"
          ],
          "IsMultipleChoice" : false,
          "AnswerContent" : "[答案] B。B项正确，第十一届冬季奥运会于1972年2月3日至13日在日本札幌举行。这是冬奥会第-次在欧洲和美国以外的地区举办，也是亚洲举办的第一届奥运会。关注公众号人才考试",
          "OptionD" : "D.索契",
          "OptionC" : "C.首尔"
        },
        {
          "OptionB" : "B.赤峰",
          "OptionA" : "A.阿勒泰",
          "TopicContent" : "7.冰雪运动历史悠久，中国的( ) 地区是“人类滑雪的起源地”。",
          "AnswerArr" : [
            "A"
          ],
          "IsMultipleChoice" : false,
          "AnswerContent" : "[答案] A。解析:中国阿勒泰地区是“人类滑雪的起源地”。",
          "OptionD" : "D.哈尔滨",
          "OptionC" : "C.大兴安岭"
        },
        {
          "OptionB" : "B.法国夏慕尼",
          "OptionA" : "A.美国普莱西德湖",
          "TopicContent" : "8.第一届冬奥会是1924年的( )冬奥会。",
          "AnswerArr" : [
            "B"
          ],
          "IsMultipleChoice" : false,
          "AnswerContent" : "[答案]B。解析: 1924 年，在法国的夏蒙尼市承办了当时被称为“冬季运动周”的运动会,两年后国际奥委会正式把其更名为第1届冬季奥林匹克运动会。",
          "OptionD" : "D.德国加尔米施-帕滕基兴",
          "OptionC" : "C.瑞士圣莫里茨"
        },
        {
          "OptionB" : "B.渥太华",
          "OptionA" : "A.维也纳",
          "TopicContent" : "9.2022年北京冬季奥运会，于2022年2月4日开幕，2月20日闭幕。北京成为了历史上第二次由首都城市承办冬奥会的城市。历史上第一次由首都城市承办冬奥会的城市是()。",
          "AnswerArr" : [
            "D"
          ],
          "IsMultipleChoice" : false,
          "AnswerContent" : "[答案]D。解析: 1952 年，第六届冬季奥运会来到了现代滑雪的诞生地一-挪威。这是冬奥会首次由在当时冬季运动最为强盛的斯堪的纳维亚地区的国家举办，奥斯陆也成为了第-一个举办冬奥会的首都城市。关注公众号人才考试",
          "OptionD" : "D.奥斯陆",
          "OptionC" : "C.华盛顿"
        },
        {
          "OptionB" : "B.国家速滑馆",
          "OptionA" : "A.首都体育馆",
          "TopicContent" : "10.北京冬奥会有多个比赛场馆，()是冬奥会产生金牌数量最多的单个场馆。",
          "AnswerArr" : [
            "B"
          ],
          "IsMultipleChoice" : false,
          "AnswerContent" : "[答案] B。解析:国家速滑馆“冰丝带”承担速度滑冰项目的比赛，共产生14块金牌，是冬奥会产生金牌数量最多的单个场馆。关注公众号人才考试",
          "OptionD" : "D.国家游泳中心",
          "OptionC" : "C.国家体育馆"
        },
        {
          "OptionB" : "B.国家速滑馆",
          "OptionA" : "A.首都体育馆",
          "TopicContent" : "11. ( )是国内第一座人工室内冰场，承担冬奧会短道速滑和花样滑冰两项重要比赛任务。",
          "AnswerArr" : [
            "A"
          ],
          "IsMultipleChoice" : false,
          "AnswerContent" : "[答案]A。解析:首都体育馆是国内第一-座人工室内冰场，承担冬奥会短道速滑和花样滑冰两项重要比赛任务。关注公众号人才考试",
          "OptionD" : "D.国家游泳中心",
          "OptionC" : "C.国家体育馆"
        },
        {
          "OptionB" : "B.故宫",
          "OptionA" : "A.圆明园",
          "TopicContent" : "12.北京冬奥村主要用于接待参加2022年北京冬奥会冰上运动的运动员。整个冬奥村以()为设计理念。",
          "AnswerArr" : [
            "C"
          ],
          "IsMultipleChoice" : false,
          "AnswerContent" : "[答案] C。解析:北京赛区的冬奥村坐落于国家体育场鸟巢附近，由20栋公寓楼组成。设计理念来自北京四合院。关注公众号人才考试",
          "OptionD" : "D.冰嬉图",
          "OptionC" : "C.四合院"
        },
        {
          "OptionB" : "B.首钢滑雪大跳台中心，",
          "OptionA" : "A.国家冬季两项中心",
          "TopicContent" : "13.北京冬奥会有多个比赛场馆，每个比赛场馆因其独特的外观都有特殊的昵称，其中被称作“雪如意”的是( ) 。",
          "AnswerArr" : [

          ],
          "IsMultipleChoice" : true,
          "AnswerContent" : "[答案]。解析:国家跳台滑雪中心主体建筑灵感来自于中国传统饰物“如意”，因此被形象地称作“雪如意”。关注公众号人才考试",
          "OptionD" : "D.国家越野滑雪中心",
          "OptionC" : "C.国家跳台滑雪中心"
        },
        {
          "OptionB" : "B.火炬采用红色和黄色作为火炬主色隐喻冰与火，象征着火炬会给冰雪世界带来“光明和温暖”",
          "OptionA" : "A.火炬的出火口共有24个",
          "TopicContent" : "14.2022年2月2日，北京2022年冬奥会火炬接力启动仪式在奥林匹克森林公园举行。关于本届冬奥会火炬，下列表述不正确的是()",
          "AnswerArr" : [
            "B",
            "D"
          ],
          "IsMultipleChoice" : true,
          "AnswerContent" : "[答案] B。解析: A项正确，火炬的出火口共有24个，既代表第二十四届冬奥会，也寓意中国传统文化习俗的24个节气。B项错误，火炬采用红色和银色作为火炬主色隐喻冰与火，象征着火炬会给冰雪世界带来“光明和温暖”。CD项正确，火炬材质选用碳纤维材料，降低了火炬重量，燃料使用氢燃料，实现火炬燃烧零排放，保证了火炬能在极寒天气中使用，体现出“绿色”办奥理念和科技冬奥的成果。关注公众号人才考试",
          "OptionD" : "D.火炬燃料使用氢燃料",
          "OptionC" : "C.火炬材质选用碳纤维材料"
        },
        {
          "OptionB" : "B.姚明",
          "OptionA" : "A.叶培建",
          "TopicContent" : "15.2022年2月2日，北京2022年冬奥会火炬接力启动仪式在奥林匹克森林公园举行。第一棒火炬手为( ) 。",
          "AnswerArr" : [
            "D"
          ],
          "IsMultipleChoice" : false,
          "AnswerContent" : "[答案]D。解析:2022年2月2日，北京2022年冬奥会火炬接力启动仪式在奥林匹克森林公园举行。第一棒火炬手为我国速度滑冰世界冠军罗致焕。[拓展]罗致焕: 1963年夺得57届世界速度滑冰锦标赛男子1500米冠军,并打破世界纪录，成为第一个获得冬季项目世界冠军的中国选手。关注公众号人才考试",
          "OptionD" : "D.罗致焕",
          "OptionC" : "C.景海鹏"
        },
        {
          "OptionB" : "B.八景宫灯",
          "OptionA" : "A.玉虚琉璃灯",
          "TopicContent" : "16.北京冬奥会火炬接力火种灯的创意源于“中华第一灯”一()。",
          "AnswerArr" : [
            "D"
          ],
          "IsMultipleChoice" : false,
          "AnswerContent" : "[答案] D。解析:北京冬奧会火炬接力火种灯的创意源于“中华第一灯”--西汉长信宫灯。“长信” ，就是永恒的信念，代表人们对光明和希望的追求和向往。关注公众号人才考试",
          "OptionD" : "D.长信宫灯",
          "OptionC" : "C.翠光两仪灯"
        },
        {
          "OptionB" : "B.短道速滑混合团体接力",
          "OptionA" : "A.女子单人雪车",
          "TopicContent" : "17. 2022年北京冬奥会新增7个小项，新增的小项不包括( )。",
          "AnswerArr" : [
            "D"
          ],
          "IsMultipleChoice" : false,
          "AnswerContent" : "[答案] D。解析: 2022 年北京冬奥会新增7个小项，包括女子单人雪车、短道速滑混合团体接力、跳台滑雪混合团体、自由式滑雪大跳台(男子、女好)、自由式滑雪空中技巧混合团体和单板滑雪障碍追逐混合团体。关注公众号人才考试",
          "OptionD" : "D.高山滑雪",
          "OptionC" : "C.跳台滑雪混合团体"
        },
        {
          "OptionB" : "B.赛事对外宣传",
          "OptionA" : "A.赛事安全管理",
          "TopicContent" : "18. 2022年1月4日，习近平在北京考察2022年冬奥会、冬残奥会筹办备赛工作时指出，对北京冬奥会、冬残奥会来讲，做好( ) 工作是最大的考验。",
          "AnswerArr" : [

          ],
          "IsMultipleChoice" : true,
          "AnswerContent" : "[答案]。解析:习近平指出，对北京冬奥会、冬残奥会来讲，做好新冠肺炎疫情防控工作是最大的考验。关注公众号人才考试",
          "OptionD" : "D.运动员服务保障",
          "OptionC" : "C.新冠肺炎疫情防控;"
        },
        {
          "OptionB" : "B.钢架雪车",
          "OptionA" : "A.跳台滑雪",
          "TopicContent" : "19. ()运动起源于阿尔卑斯山地域，被誉为“冬奥会皇冠上的明珠”和“勇敢者的运动”。",
          "AnswerArr" : [
            "D"
          ],
          "IsMultipleChoice" : false,
          "AnswerContent" : "[答案] D。高山滑雪运动起源于阿尔卑斯山地域，被誉为“冬奥会皇冠上的明珠”和“勇敢者的运动”。关注公众号人才考试",
          "OptionD" : "D.高山滑雪",
          "OptionC" : "C.越野滑雪"
        },
        {
          "OptionB" : "B.共享办奥",
          "OptionA" : "A.绿色办奥",
          "TopicContent" : "20.2015年8月20日，习近平总书记主持召开中共中央政治局常委会会议，提出了坚持( ) 的要求。其中，开放办奥是总书记“推动构建人类命运共同体”理念的具体体现。",
          "AnswerArr" : [
            "C"
          ],
          "IsMultipleChoice" : false,
          "AnswerContent" : "[答案] C。开放办奥是总书记“推动构建人类命运共同体”理念的具体体现。关注公众号人才考试",
          "OptionD" : "D.廉洁办奥",
          "OptionC" : "C.开放办奥"
        },
        {
          "OptionB" : "B.速度滑冰",
          "OptionA" : "A.短道速滑",
          "TopicContent" : "21.在滑冰运动中，历史最为悠久，开展最为广泛的是( )。",
          "AnswerArr" : [

          ],
          "IsMultipleChoice" : true,
          "AnswerContent" : "[答案]。速度滑冰源自北欧，简称速滑，在滑冰运动中历史最为悠久，开展最为广泛，是以冰刀为工具在冰上进行的一种冰上竞速运动。关注公众号人才考试.",
          "OptionD" : "D.花样滑冰",
          "OptionC" : "C.山地滑冰"
        },
        {
          "OptionB" : "B.张北",
          "OptionA" : "A.北奧",
          "TopicContent" : "22.为贯彻生态办奧的理念，北京冬奥会期间，3大赛区26个场馆将全部使用绿色电能，这也将成为奥运历史上首次实现全部场馆100%绿色电能供应。场馆使用的“绿电”来源于( ) 可再生能源柔性直流电网试验示范工程。",
          "AnswerArr" : [

          ],
          "IsMultipleChoice" : true,
          "AnswerContent" : "[答案]。场馆使用的“绿电”来源于张北可再生能源柔性直流电网试验示范工程。",
          "OptionD" : "D.延北",
          "OptionC" : "C.张延"
        },
        {
          "OptionB" : "B.车顶采用光伏能源",
          "OptionA" : "A.车载平台采用氢动力",
          "TopicContent" : "23.给雪板打蜡，是滑雪运动中非常重要的服务技术。打蜡后的雪板就像一辆“方向盘很轻的车”，不仅能帮助运动员节省体力，而且更易操控。由山东省自主研发出的首台集新一代信息技术于一身的国产雪蜡车于2021年9月正式下线。关于雪蜡车，下列表述不正确的是( ) 。",
          "AnswerArr" : [
            "D",
            "B"
          ],
          "IsMultipleChoice" : true,
          "AnswerContent" : "[答案] D。AB项正确，雪蜡车以低碳环保为目标，车载平台采用氢动力，车顶采用光伏能源。C项错误，D项错误，雪蜡车主体结构采用了中国高铁车厢成型技术，车厢完全由铝合金制作，较钢质产品减重4吨以上。关注公众号人才考试",
          "OptionD" : "D.车厢完全由钛合金制作",
          "OptionC" : "C.雪蜡车主体结构采用了中国高铁车厢成型技术"
        },
        {
          "OptionB" : "B.时代雪车",
          "OptionA" : "A.解放雪车",
          "TopicContent" : "24.2021年11月11日，中国一汽与中国航天科技集团联合向国家体育总局冬运中心交付国产雪车一- ( ) 。这次交付实现了国产雪车“零”的突破。",
          "AnswerArr" : [
            "C"
          ],
          "IsMultipleChoice" : false,
          "AnswerContent" : "[答案]C。2021年11月11日，中国一汽与中国航天科技集团联合向国家体育总局冬运中心交付国产雪车一-红旗雪车。这次交付实现了国产雪车“零”的突破。",
          "OptionD" : "D.一汽雪车",
          "OptionC" : "C.红旗雪车"
        },
        {
          "OptionB" : "B.叶乔波",
          "OptionA" : "A.杨扬",
          "TopicContent" : "25.在冬奥历史上，中国队第一枚金牌是由( ) 获得的。",
          "AnswerArr" : [
            "A"
          ],
          "IsMultipleChoice" : false,
          "AnswerContent" : "[答案]A。2002年盐湖城冬奥会，杨扬在短道速滑女子500米项目中问鼎，实现了中国冬奥金牌零的突破。关注公众号人才考试",
          "OptionD" : "D.王檬",
          "OptionC" : "C.李佳军"
        },
        {
          "OptionB" : "B.硅化钠火炬",
          "OptionA" : "A.磷质火炬",
          "TopicContent" : "26.2022年2月2日,北京冬奥会火炬在北京冬奥公园、首钢园传递，其中，最引人注目的是奥运史上首次机器人与机器人之间在水下的火炬传递。不同于其他手持火炬，水陆两栖机器人手握的是国际上首只无烟燃烧的绿色清洁()，以此为基础，才能实现水下对接点火。",
          "AnswerArr" : [
            "D"
          ],
          "IsMultipleChoice" : false,
          "AnswerContent" : "[答案]D。不同于其他手持火炬，水陆两栖机器人手握的是国际上首只无烟燃烧的绿色清洁水空跨介质火炬，以此为基础，才能实现水下对接点火。机器人传递的特种火炬,在下水前能够自主补氧,就可以在水下不依赖空气中的氧气。",
          "OptionD" : "D.水空跨介质火炬",
          "OptionC" : "C.纯氢火炬"
        },
        {
          "OptionB" : "B.黑金",
          "OptionA" : "A.二氧化锰",
          "TopicContent" : "27.2021年12月31日，北京2022年冬奥会颁奖礼服发布。为了让颁奖礼仪服装达到美观又保暖,在衣服里特意添加了一片片黑色的材料，可以实现快速升温。这种材料是()。",
          "AnswerArr" : [

          ],
          "IsMultipleChoice" : true,
          "AnswerContent" : "[答案]。这种黑色的材料，是中国航发为本届冬奥会研发的石墨烯发热材料，可以实现快速升温。关注公众号人才考试",
          "OptionD" : "D.稀土",
          "OptionC" : "C.石墨烯"
        },
        {
          "OptionB" : "B.中轴神韵",
          "OptionA" : "A.冰雪秀带",
          "TopicContent" : "28.2月2日，北京奥运会火炬传递开始。其中北京冬奥公园的点位主题为",
          "AnswerArr" : [
            "A"
          ],
          "IsMultipleChoice" : false,
          "AnswerContent" : "[答案] A。北京冬奥公园的点位主题为“冰雪秀带”，核心内涵为体现双奥之城的独特魅力，展示三亿人参与冰雪运动成果，是北京夏季、冬季体育项目.均衡发展的标志。关注公众号人才考试",
          "OptionD" : "D.大众冰雪.",
          "OptionC" : "C.民族之脊"
        },
        {
          "OptionB" : "B.美国普莱西德湖",
          "OptionA" : "A.法国阿尔贝维尔",
          "TopicContent" : "29.中国首次参加的冬奥会是( ) 冬奥会。",
          "AnswerArr" : [
            "B"
          ],
          "IsMultipleChoice" : false,
          "AnswerContent" : "[答案] B。1980年，第十三届冬奥会在美国普莱西德湖举行，中国奥委会是1979年在国际奥委会合法席位得到恢复后首次出席冬季奥运会。",
          "OptionD" : "D.加拿大卡尔加里",
          "OptionC" : "C.南斯拉夫萨拉热窝"
        },
        {
          "OptionB" : "B.高亭宇",
          "OptionA" : "A.武大靖",
          "TopicContent" : "30. 2018年平昌冬奥会上，( ) 首夺短道冬奥冠军，为中国代表团赢得平昌冬奥会上的首枚也是唯一一 -枚 金牌。",
          "AnswerArr" : [
            "A"
          ],
          "IsMultipleChoice" : false,
          "AnswerContent" : "[答案] A。2018年平昌冬奥会上，武大靖首夺短道冬奥冠军，为中国代表团赢得平昌冬奥会上的首枚也是唯一一-枚金牌。关注公众号人才考试",
          "OptionD" : "D.李佳军",
          "OptionC" : "C.罗致焕"
        },
        {
          "OptionB" : "B.高山滑雪",
          "OptionA" : "A.冬季两项",
          "TopicContent" : "31.冬奥会上唯一-一个只设男子比赛的项目是( ) 。",
          "AnswerArr" : [

          ],
          "IsMultipleChoice" : true,
          "AnswerContent" : "[答案]。北欧两项由越野滑雪和跳台滑雪组成，又称北欧全能，是冬奥会上唯一--一个只设男子比赛的项目。关注公众号人才考试",
          "OptionD" : "D.单板滑雪",
          "OptionC" : "C.北欧两项"
        },
        {
          "OptionB" : "B.腋下创可贴",
          "OptionA" : "A.气溶胶采集器",
          "TopicContent" : "32.北京冬奥会防疫工作十分重要，对此我国也做了很充分的准备。其中( )是一种可穿戴的智能体温计，大概只有手指肚大小，是现在世界上体积最小、精度最高的可穿戴式连续智能测温仪。关注公众号人才考试",
          "AnswerArr" : [
            "C"
          ],
          "IsMultipleChoice" : false,
          "AnswerContent" : "[答案]。腋下创可贴是一种可穿戴的智能体温计，大概只有手指肚大小，是现在世界.上体积最小、精度最高的可穿戴式连续智能测温仪，其中测温的芯片只有米粒那么大的，而精度达到了0. 05°C以内，充一次电就可以用10天。",
          "OptionD" : "D. AOP-KF固体碱",
          "OptionC" : "C.防疫员机器人"
        },
        {
          "OptionB" : "B.二氧化氮",
          "OptionA" : "A.氧化亚氯",
          "TopicContent" : "33. 啊OP-KF固体碱是一种独特的空气净化材料，在应对新冠状病毒、甲型H1N1流感病毒等微生物病毒时，具有良好的杀菌灭活的作用，尤其是在对付新冠病毒方面，它的灭活率能达到99%。在消灭病毒的过程之中，会释放出微量的()。",
          "AnswerArr" : [
            "D"
          ],
          "IsMultipleChoice" : false,
          "AnswerContent" : "[答案] D。在消灭病毒的过程之中，AOP-KF 固体碱会释放出微量的二氧化氯。二氧化氯是唯一可以用作食品添加剂的消毒剂，它对病毒最为敏感，而且是越敏感，越容易杀灭，这就导致它可以很好地杀灭病毒，这也被认为是最安全的消毒方法。关注公众号人才考试",
          "OptionD" : "D.二氧化氯",
          "OptionC" : "C.氧化亚氯"
        },
        {
          "OptionB" : "B.排泄物",
          "OptionA" : "A.尿检",
          "TopicContent" : "34.为维护公平竞争的奥林匹克精神，2022 年北京冬奥会首次使用( )兴奋剂检测技术。",
          "AnswerArr" : [
            "D",
            "B"
          ],
          "IsMultipleChoice" : true,
          "AnswerContent" : "[答案]D。为维护公平竞争的奥林匹克精神，2022年北京冬奥会首次使用王血点(DBS) 兴奋剂检测技术。关注公众号人才考试",
          "OptionD" : "D.干血点",
          "OptionC" : "C.气溶胶"
        },
        {
          "OptionB" : "B.会火",
          "OptionA" : "A.淡火",
          "TopicContent" : "35.2022年2月4日，第二十四届冬季奥林匹克运动会开幕式在北京国家体育场举行。点火方式是由最后一棒的手持火炬转化为主火炬，主火炬在奥运历史上首次使用“( )”方式，充分体现了绿色环保的理念。",
          "AnswerArr" : [
            "D"
          ],
          "IsMultipleChoice" : false,
          "AnswerContent" : "[答案] D。点火方式是由最后一棒的手持火炬转化为主火炬，主火炬在奥运历史.上首次使用_“微火”方式，充分体现了绿色环保的理念。",
          "OptionD" : "D.微火",
          "OptionC" : "C.明火."
        },
        {
          "OptionB" : "B.一块冰",
          "OptionA" : "A.青花瓷",
          "TopicContent" : "36.2022年2月4日，第二十四届冬季奥林匹克运动会开幕式在北京国家体育场举行。这次的开幕焰火，第一次在空中呈现了“( ) ”的造型，以此来表达对全世界来宾的欢迎。关注公众号人才考试",
          "AnswerArr" : [

          ],
          "IsMultipleChoice" : true,
          "AnswerContent" : "[答案]。长期以来，“迎客松” 成为了中国人心中欢迎贵客的象征。这次的开幕焰火，第一次在空中呈现了“迎客松”的造型，以此来表达对全世界来宾的欢迎。关注公众号人才考试",
          "OptionD" : "D.和平鸽",
          "OptionC" : "C.迎客松."
        },
        {
          "OptionB" : "B.速度滑冰",
          "OptionA" : "A.越野滑雪",
          "TopicContent" : "37.在北京冬奥会的15个项目中，产生金牌最多的项目是( ) 。",
          "AnswerArr" : [
            "B"
          ],
          "IsMultipleChoice" : false,
          "AnswerContent" : "[答案]B。在北京冬奥会的15个项目中，产生金牌最多的项目是速度滑冰，共产生14枚金牌。关注公众号人才考试",
          "OptionD" : "D.越野滑雪",
          "OptionC" : "C.自由式滑雪"
        },
        {
          "OptionB" : "B.降低空气阻力",
          "OptionA" : "A.迅速提速",
          "TopicContent" : "38.短道速滑是大家喜闻乐见的冬奥项目。看过比赛的朋友会发现，运动员们在滑冰过程中的姿态变换很奇妙:时而摆臂疾跑，时而双手背后，时而单手扶地。其中双手背后的动作主要是为了(",
          "AnswerArr" : [
            "B"
          ],
          "IsMultipleChoice" : false,
          "AnswerContent" : "[答案] B。摆臂姿势常出现在起步及直道加速时，运动员大幅摆臂，脚下蹬冰，迅速提速。在直道巡航时则会转为背手滑，从而减少自身迎风面积，降低空气阻力，以省力状态维持高速滑行。而在紧张刺激的过弯阶段，大家都会俯身摸地。通过手撑地面，增大冰刀与冰面的摩擦力，以提供更大的向心力，从而让人能以更高的速度过弯滑行，不至于偏离轨道。关注公众号人才考试",
          "OptionD" : "D.减小惯性",
          "OptionC" : "C.增大与冰面的摩擦力"
        },
        {
          "OptionB" : "B.石墨",
          "OptionA" : "A.碳纤维",
          "TopicContent" : "39.冰壶运动中，冰壶刷是选手们用来融化冰面的工具。当今赛场.上使用的冰壶扫帚多为()材料制成的冰壶刷。",
          "AnswerArr" : [
            "A"
          ],
          "IsMultipleChoice" : false,
          "AnswerContent" : "[答案]A。冰壶刷是选手们用来融化冰面的工具。当今赛场.上使用的冰壶扫帚多为碳纤维材料制成的冰壶刷。通过扫刷冰面，减少冰壶和冰面的摩擦，以让冰壶滑得更远，还能改变滑行方向。关注公众号人才考试，",
          "OptionD" : "D.水晶",
          "OptionC" : "C.二氧化硅."
        },
        {
          "OptionB" : "B.短道速滑女子500米",
          "OptionA" : "A.短道速滑混合团体2000米接力",
          "TopicContent" : "40. 2022年2月5日，在北京冬奥会( ) 决赛中，中国队成功夺冠，为中国体育代表团夺得本届冬奥会首金。",
          "AnswerArr" : [
            "A"
          ],
          "IsMultipleChoice" : false,
          "AnswerContent" : "[答案]A。2月5日，在北京2022年冬奥会短道速滑混合团体2000米接力决赛中，中国选手武大靖、任子威、范可新、曲春雨以2分37秒348的成绩夺得冠军，为中国队拿下本届冬奥会上的首枚金牌。关注公众号人才考试",
          "OptionC" : "C.冬奥会越野滑雪女子双追逐赛D.速度滑冰女子3000米决赛"
        },
        {
          "OptionB" : "B.李文龙",
          "OptionA" : "A.任子威",
          "TopicContent" : "41.2022年2月7日，在北京冬奥会短道速滑男子1000米决赛上，中国选手( )以1分26秒768夺冠，这是中国选手首次夺得该项目冬奥会金牌。",
          "AnswerArr" : [
            "A"
          ],
          "IsMultipleChoice" : false,
          "AnswerContent" : "[答案] A。2月7日，在北京冬奥会男子1000米决赛上，中国选手任子威以1分26秒768夺冠，这是中国选手首次夺得该项目冬奥会金牌。关注公众号人才考试",
          "OptionD" : "D.武大靖，",
          "OptionC" : "C.刘少林"
        },
        {
          "OptionB" : "B.首钢滑雪大跳台中心",
          "OptionA" : "A.国家速滑馆",
          "TopicContent" : "42. ( ) 是冬奥历史.上第一-座与工业遗产再利用直接结合的竞赛场馆。",
          "AnswerArr" : [
            "B"
          ],
          "IsMultipleChoice" : false,
          "AnswerContent" : "[答案] B。首钢滑雪大跳台是单板大跳台运动在全球的第一座 永久跳台,也是冬奥历史上第一座与工业遗产再利用直接结合的竞赛场馆。关注公众号人才考试",
          "OptionD" : "D.国家体育馆",
          "OptionC" : "C.五棵松体育中心"
        },
        {
          "OptionB" : "B.节能建筑",
          "OptionA" : "A.健康建筑",
          "TopicContent" : "43.北京冬奥村秉承“绿色办奥”理念，采用国际领先的“( ) ”金级标准设计建造，可为居住者提供舒适、健康的居住环境。",
          "AnswerArr" : [
            "A"
          ],
          "IsMultipleChoice" : false,
          "AnswerContent" : "[答案] A。北京冬奥村秉承“绿色办奥”理念，采用国际领先的_“健康建筑”金级标准设计建造，可为居住者提供舒适、健康的居住环境。关注公众号人才考试",
          "OptionD" : "D.低耗建筑",
          "OptionC" : "C.绿色建筑"
        },
        {
          "OptionB" : "B.5G+8K",
          "OptionA" : "A.5G+4K",
          "TopicContent" : "44.北京冬奥会转播是史上科技含量最高的奥运会，采用的是( ) 的技术对赛事进行转播。",
          "AnswerArr" : [
            "B"
          ],
          "IsMultipleChoice" : false,
          "AnswerContent" : "[答案]B。与此前的冬奥会相比，北京冬奥会将利用最新的科技手段，为全世界的观众提供前所未有的现场转播和全方位覆盖报道。北京冬奥会转播将成为史上科技含量最高的奥运会。北京冬奥会采用5G+8K的技术对赛事进行转播。关注公众号人才考试",
          "OptionD" : "D.6G+16K",
          "OptionC" : "C.6G+8K"
        },
        {
          "OptionB" : "B.中国电信",
          "OptionA" : "A.中国网通",
          "TopicContent" : "45. ( ) 是冬奥会唯一官方通信服务合作伙伴，为冬奥会提供了安全可靠、稳定畅通的5G通信保障。",
          "AnswerArr" : [
            "D"
          ],
          "IsMultipleChoice" : false,
          "AnswerContent" : "[答案] D。虫国联通作为冬奥会唯-官方通信服务合作伙伴，研发了多频段、多形态的5G基站设备，在冬奥雪上场馆建成了可抵抗高寒、强风等恶劣条件的5G全覆盖网络,为冬奥会提供了安全可靠、稳定畅通的5G通信保障。关注公众号人才考试",
          "OptionD" : "D.中国联通",
          "OptionC" : "C.中国移动"
        },
        {
          "OptionB" : "B.风压雪",
          "OptionA" : "A.流体雪",
          "TopicContent" : "46.为实现用雪自由，国家高山滑雪中心赛道采用( ) 赛道，这也是高山滑雪赛道的一大特色。",
          "AnswerArr" : [
            "C"
          ],
          "IsMultipleChoice" : false,
          "AnswerContent" : "[答案] C。国家高山滑雪中心赛道采用冰状雪赛道，冰状雪是高山滑雪赛道的一大特色。自然雪的密度在0.05到0.15克每立方厘米，非常松软。而冰状雪的密度是自然雪的5到13倍，表面有一层薄的硬冰壳，是雪又似冰。用冰状雪铺设的雪道，表面保持着结晶状态，近似于冰面，能满足国际标准对雪道厚度、硬度、密度、表面温度、雪粒径、含水量等的要求。关注公众号人才考试",
          "OptionD" : "D.高压雪公众号.",
          "OptionC" : "C.冰状雪"
        },
        {
          "OptionB" : "B.绿色冬奥",
          "OptionA" : "A.精彩冬奥",
          "TopicContent" : "47. 2022年北京冬季奥运会主题花坛，是为迎接冬奥设置的花坛，其中天安门广场的花坛主题是( )",
          "AnswerArr" : [
            "A"
          ],
          "IsMultipleChoice" : false,
          "AnswerContent" : "[答案] A。天安门广场中心布置_“精彩冬奥”主题花坛，花坛顶高17米，以中国结为主景，结合冬奥会会徽以及冰雪元素，传达对北京冬奥会美好祝福。",
          "OptionD" : "D.冰天雪地.",
          "OptionC" : "C.欢天喜地"
        },
        {
          "OptionB" : "B.陈虹伊",
          "OptionA" : "A.杜佳妮",
          "TopicContent" : "48.2022年2月8日，自由式滑雪女子大跳台决赛，我国选手( ) 首次跳出1620超高难度创造历史摘金。",
          "AnswerArr" : [
            "D"
          ],
          "IsMultipleChoice" : false,
          "AnswerContent" : "[答案]D。2月8日，自由式滑雪女子大跳台决赛，我国选手谷爱凌首次跳出1620超高难度创造历史摘金。关注公众号人才考试",
          "OptionD" : "D.谷爱凌",
          "OptionC" : "C.韩雨"
        },
        {
          "OptionB" : "B.冰雕艺术",
          "OptionA" : "A.燕京八绝",
          "TopicContent" : "49. 2022年北京冬奥会体育图标共24个。图标设计，以中国汉字为灵感来源，以( ) 为主要呈现形式。",
          "AnswerArr" : [
            "C"
          ],
          "IsMultipleChoice" : false,
          "AnswerContent" : "[答案] C。2022 年北京冬奥会体育图标共24个。图标设计，以中国汉字为灵感来源，以篆刻艺术为主要呈现形式，将冬季运动元素与中国传统文化巧妙结合，既展现出冬季运动挑战自我、追求卓越的特点，也凝聚了中国传统文化的厚重与精深，彰显了北京冬奥会和冬残奥会的理念和愿景。关注公众号人才考试",
          "OptionD" : "D.中国结",
          "OptionC" : "C.篆刻艺术."
        },
        {
          "OptionB" : "B.奉献、爱与微笑",
          "OptionA" : "A.奉献、友爱、互助、进步",
          "TopicContent" : "50.志愿者是奥林匹克运动的基石，冬奥会志愿者标志上半部图形由寓意连胜的“VVV” 组成，下半部分“笑脸”表达了“() ”的主题。",
          "AnswerArr" : [
            "B"
          ],
          "IsMultipleChoice" : false,
          "AnswerContent" : "[答案] B。志愿者标志上半部图形由寓意连胜的“VV\" 组成，象征志愿者“手拉手”参与冬奥服务冬奥的热情;图形下半部分“笑脸”表达了“奉献、爱与微笑”的主题。关注公众号人才考试",
          "OptionD" : "D.和平、进步、发展",
          "OptionC" : "C.团结、友爱、互助"
        }
      ]
    },
    {
      "ModuleTitile" : "模块2: 多选题部分",
      "ModuleContentArr" : [
        {
          "OptionB" : "B.元代人的骑木运动，即是滑雪、滑冰",
          "OptionA" : "A.早在三国两晋时期，中国汉族人民就掌握了冰雪运动",
          "TopicContent" : "1.冰雪运动在中国古代也是一项热门运动。关于中国古代冰雪运动发展，下列表述正确的是(",
          "AnswerArr" : [
            "B",
            "C"
          ],
          "IsMultipleChoice" : true,
          "AnswerContent" : "[答案] BC。A项错误，早在隋唐时期，我国北方的少数民族中，就掌握了冰雪运动。东北地区的女真族曾经发明了-种滑冰的竹马，人踏在竹马上，手执曲棍，在冰面上滑行。这是中国人最早的滑冰的方式之一。B项正确，元代人的骑木，即是滑雪、滑冰。C项正确，1625年 (明熹宗天启五年)正月初二，东北建州女真的首领努尔哈赤，举行了盛大的冰.上运动会，第一个项目是冰球，然后又进行花样滑冰表演。当时，冠军获赏银二十两，亚军十两，这是中国有文献记载的第一次冰上运动会。D项错误，乾隆帝在《冰嬉赋序》里曾将冰上运动“冰嬉”称为“国俗”。“冰嬉” 不仅是一种娱乐，同时也是重要的军事训练。关注公众号人才考试",
          "OptionD" : "D.康熙帝在曾将冰上运动“冰嬉”称为“国俗”",
          "OptionC" : "C.中国有文献记载的第一次冰上运动会是努尔哈赤举办的"
        },
        {
          "OptionB" : "B.韩梅",
          "OptionA" : "A.高亭宇",
          "TopicContent" : "2.2022年1月30日，北京冬奥会开幕式中国体育代表团旗手公布，分别是)。",
          "AnswerArr" : [
            "A",
            "D"
          ],
          "IsMultipleChoice" : true,
          "AnswerContent" : "[答案]AD。1月30日，北京冬奥会开幕式中国体育代表团旗手公布，分别是中国男子速度滑冰运动员高亭宇和中国女子钢架雪车运动员赵丹。关注公众号人才考试.",
          "OptionD" : "D.赵丹",
          "OptionC" : "C.李奇时"
        },
        {
          "OptionB" : "B.挪威奥斯陆",
          "OptionA" : "A.瑞士圣莫里茨",
          "TopicContent" : "3.冬奥会历史上，有多个城市曾两次举办冬奥会，包括()",
          "AnswerArr" : [
            "A",
            "C",
            "D"
          ],
          "IsMultipleChoice" : true,
          "AnswerContent" : "[答案] ACD。 瑞士圣莫里茨、奥地利因斯布鲁克和美国普莱西德湖三地均举办过两届冬奥会。",
          "OptionD" : "D.美国普莱西德湖",
          "OptionC" : "C.奥地利因斯布鲁克"
        },
        {
          "OptionB" : "B.日本",
          "OptionA" : "A.奥地利",
          "TopicContent" : "4.2022年北京冬季奥运会，于2022年2月4日开幕，2月20日闭幕。北京成为全球首座既举办过夏奥会，又举办过冬奥会的“双奥之城”。历史.上同时举办过冬奥会和夏奥会的国家有()。",
          "AnswerArr" : [
            "D"
          ],
          "IsMultipleChoice" : false,
          "AnswerContent" : "[答案]D。迄今为止，同时举办过夏奧和冬奧的国家有美国、日本、法国、德国、意大利、加拿大、俄罗斯(苏联)、韩国和中国。关注公众号人才考试",
          "OptionD" : "D.加拿大",
          "OptionC" : "C.瑞士"
        },
        {
          "OptionB" : "B.首都体育馆",
          "OptionA" : "A.五棵松体育中心",
          "TopicContent" : "5.北京冬奥会共有四个“双奥场馆”，即同时举办过夏季和冬季奥运会的场馆，下列属于“双奥场馆”的是( ) 。",
          "AnswerArr" : [
            "B",
            "C",
            "D"
          ],
          "IsMultipleChoice" : true,
          "AnswerContent" : "[答案] BCD。北京冬奥会共有四个“双奥场馆”，即同时举办过夏季和冬季奥运会的场馆，包括国家体育场、国家体育馆、国家游泳中心、首都体育馆。",
          "OptionD" : "D.国家体育场.",
          "OptionC" : "C.国家体育馆"
        },
        {
          "OptionB" : "B.首钢滑雪大跳台中心一-一水晶鞋",
          "OptionA" : "A.国家速滑馆一一冰丝带",
          "TopicContent" : "6.北京冬奥会有多个比赛场馆,每个比赛场馆因其独特的外观都有特殊的昵称，下列场馆与其昵称对应正确的是()。",
          "AnswerArr" : [
            "A",
            "B"
          ],
          "IsMultipleChoice" : true,
          "AnswerContent" : "[答案] AB。A项正确，国家速滑馆的昵称是“冰丝带”。B项正确，首钢滑雪大跳台中心被称作“雪飞天”、“水晶鞋”。项错误，五棵松体育中心外形仿佛被无数片飘落的雪花包裹，有“冰菱花”之称。D项错误，国家体育馆外形设计类似于传统的中国折扇，因此有“折扇”的绰号，也有“冰之帆”的昵称。关注公众号人才考试",
          "OptionD" : "D.国家体育馆一-冰菱花",
          "OptionC" : "C.五棵松体育中心一一冰之帆"
        },
        {
          "OptionB" : "B.北京2022年冬残奥会会徽名为“飞跃”",
          "OptionA" : "A.北京冬奥会的主题口号是一起点亮梦",
          "TopicContent" : "7.关于北京2022冬奥会赛事文化，下列表述不正确的是",
          "AnswerArr" : [
            "A",
            "C"
          ],
          "IsMultipleChoice" : true,
          "AnswerContent" : "[答案] AC。 A项错误，2021 年9月17日，北京冬奥会、冬残奥会发布主.题口号一-_“一起向未来”。B项正确，北京2022年冬奥会会徽名为“冬梦”，冬残奥会会徽名为_“飞跃”。C项错误，北京冬奥会吉祥物名为_“冰墩墩”，冬残奥会吉祥物名为“雪容融”。D项正确，北京2022年冬奥会火炬，名为“飞扬”，颜色为银色与红色。关注公众号人才考试",
          "OptionD" : "D.北京2022年冬奥会火炬名为“飞扬”",
          "OptionC" : "C.北京冬奧会吉祥物名为“雪容融”"
        },
        {
          "OptionB" : "B.月季一坚韧",
          "OptionA" : "A.玫瑰一一友爱",
          "TopicContent" : "8.北京冬奥会和冬残奥会采用手工绒线编结花束作为颁奖花束,在奖牌颁发仪式中与奖牌一同颁发给获奖运动员。每种花束有着不同的寓意，对应正确的是",
          "AnswerArr" : [
            "A",
            "B",
            "C",
            "D"
          ],
          "IsMultipleChoice" : true,
          "AnswerContent" : "[答案] ABCD。北京冬奥会颁奖花束包括玫瑰、月季、铃兰、绣球、月桂和橄榄6种寓意美好的花型，分别象征着友爱、坚韧、幸福、团结、胜利与和平。",
          "OptionD" : "D.绣球一一团结",
          "OptionC" : "C.铃兰--幸福."
        },
        {
          "OptionB" : "B.冰壶",
          "OptionA" : "A.冰球",
          "TopicContent" : "9.北京冬季奥运会设7个大项，15个分项，109 个小项，下列属于7个大项的是()。",
          "AnswerArr" : [
            "A",
            "B",
            "D"
          ],
          "IsMultipleChoice" : true,
          "AnswerContent" : "[答案] ABD。7 个大项为:滑雪、滑冰、冰球、冬季两项(越野滑雪射击比赛)、雪车、雪橇、冰壶。",
          "OptionD" : "D.雪橇",
          "OptionC" : "C.现代两项"
        },
        {
          "OptionB" : "B.是世界上第一条 最高设计速度350千米\/小时的高寒高速铁路",
          "OptionA" : "A.是中国第一条采用自主研发的北斗卫星导航系统的铁路",
          "TopicContent" : "10.京张高速铁路是2022年北京冬奥会的重要交通保障设施。关于京张高铁，下列说法正确的是()。",
          "AnswerArr" : [
            "A",
            "B",
            "C",
            "B",
            "C"
          ],
          "IsMultipleChoice" : true,
          "AnswerContent" : "[答案]ABC。ABC项正确，京张高速铁路是2022年北京冬奥会的重要交通,保障设施，是中国第一条采用自主研发的北斗卫星导航系统、设计速度350千米\/小时的智能化高速铁路,也是世界上第一条最高设计速度350千米\/小时的高寒、大风沙高速铁路。D项错误，京张高铁太子城站位于张家口赛区核心区内，是世界上首个直通奥运赛场的高铁站。关注公众号人才考试",
          "OptionD" : "D.京张高铁太子城站位于延庆赛区核心区内,是世界上首个直通奥运赛场的高铁站",
          "OptionC" : "C.京张高铁实现5G信号覆盖"
        },
        {
          "OptionB" : "B.北京是首个大规模使用当今最环保氢气制冰技术的冬奥会主办城市",
          "OptionA" : "A.国家体育馆建有全球第一条360度回旋赛道",
          "TopicContent" : "11.在疫情背景下，北京冬奥会作为“奥运新标杆”的意义彰显无疑，它将成为世界冰雪运动发展的里程碑。关于本届北京冬奥会创造的历史，下列表述正确的是()。",
          "AnswerArr" : [
            "C",
            "D"
          ],
          "IsMultipleChoice" : true,
          "AnswerContent" : "[答案] CD。A项错误，国家雪车雪橇中心建有全球第一条360度回旋赛道。B项错误，北京是首个大规模使用当今最环保二氧化碳制冰技术的冬奥会主办城市。C项正确，参加北京冬奥会的运动员中女性比例超过45%，历史首次。D项正确，北京冬奥会100%使用绿色清洁电能，历史首次。",
          "OptionD" : "D.北京冬奥会100%使用绿色清洁电能",
          "OptionC" : "C.参加北京冬奥会的运动员中女性比例超过45%，历史首次"
        },
        {
          "OptionB" : "B.二氧化碳跨临界直冷制冰技术除了绿色环保，最大优点就是冰温均匀",
          "OptionA" : "A.二氧化碳制冷剂的全球变暖潜能值(GWP) 为1",
          "TopicContent" : "12.国家速滑馆、首都体育馆等4个冰上场馆选用了二氧化碳跨临界直冷制冰技术，极大降低了制冷过程的碳排放，这也是该技术首次在冬奥会上使用。关于该技术，下列表述正确的是( ) 。",
          "AnswerArr" : [
            "A",
            "B",
            "D"
          ],
          "IsMultipleChoice" : true,
          "AnswerContent" : "[答案]ABD。A项正确，在国家速滑馆、首都体育馆等四个冰上场馆，均采用了全球变暖潜能值(GWP) 为1的二氧化碳制冷剂。B项正确，和传统的制冰技术相比，最明显的区别是此次采用二氧化碳跨临界直冷制冰系统制出来的约5500平方米的冰面，冰温很均匀。C项错误，D项正确，直冷制冰避免了使用载冷剂换热所造成的能量损失，传热系数和制冷效率都很高。关注公众号人才考试[拓展]全球变暖潜能值(GWP) 又称全球增温潜势，是基于充分混合的温室气体辐射特性的一个指数，用于衡量相对于二氧化碳的，在所选定时间内进行积分的，当前大气中某个给定的充分混合的温室气体单位质量的辐射强迫。",
          "OptionD" : "D.直冷制冰传热系数和制冷效率都很高",
          "OptionC" : "C.直冷制冰需要借助一定数量的载冷剂"
        },
        {
          "OptionB" : "B.蓝白色调.",
          "OptionA" : "A.黄蓝色调，",
          "TopicContent" : "13.北京冬奥会核心图形对应色彩系统划分为三个色系，分别是()。",
          "AnswerArr" : [
            "B",
            "C",
            "D"
          ],
          "IsMultipleChoice" : true,
          "AnswerContent" : "[答案] BCD。北京冬奥会核心图形对应色彩系统划分为三个色系，分别是:寓意纯洁冰雪、未来与梦想的蓝白色调;体现运动激情、春节节庆氛围的红金色调;代表文化和可持续的青绿色调。关注公众号人才考试",
          "OptionD" : "D.红金色调",
          "OptionC" : "C.青绿色调"
        },
        {
          "OptionB" : "B.廉洁",
          "OptionA" : "A.科技",
          "TopicContent" : "14.北京冬奥会的特色是( ) 。",
          "AnswerArr" : [
            "A",
            "D"
          ],
          "IsMultipleChoice" : true,
          "AnswerContent" : "[答案] AD。习近平指出，要坚持绿色办奥、共享办奥、开放办奥、廉洁办奧的理念，突出科技、智慧、绿色、节俭特色。",
          "OptionD" : "D.节俭",
          "OptionC" : "C.开放"
        },
        {
          "OptionB" : "B.短道速滑运动起源于加拿大",
          "OptionA" : "A.短道速滑赛道被标志线分为内道和外道，选手需按规则滑行",
          "TopicContent" : "15.2月5日，在北京2022年冬奥会短道速滑混合团体2000米接力决赛中，中国选手武大靖、任子威、范可新、曲春雨以2分37秒348的成绩夺得冠军，为中国队拿下本届冬奥会上的首枚金牌。关于短道速滑，下列说法不正确的是",
          "AnswerArr" : [
            "A",
            "C",
            "D"
          ],
          "IsMultipleChoice" : true,
          "AnswerContent" : "[答案] ACD。 A项错误，速度滑冰(不含集体出发)赛道被标志线分为内道和外道，选手需按规则滑行，一圈内道一圈外道;而短道速滑赛道则没有细分，选手可任意滑行，不存在串道。B项正确，C项错误，短道速滑19世纪80年代起源于加拿大，是在长度较短的跑道上进行的冰上竞速运动。D项错误，花样滑冰18世纪诞生于英国，把惊险和美丽发挥到极致，被称为“运动的诗”。关注公众号人才考试",
          "OptionD" : "D.短道速滑被称为“运动的诗”",
          "OptionC" : "C.短道速滑是一种冰上技巧运动"
        },
        {
          "OptionB" : "B.金凤凰",
          "OptionA" : "A.金龙",
          "TopicContent" : "16.北京冬奥会火炬接力标志创意来源于中国传统文化中的( ) 。",
          "AnswerArr" : [
            "B",
            "C"
          ],
          "IsMultipleChoice" : true,
          "AnswerContent" : "[答案] BC。标志创意来源于中国传统文化中的“金凤凰”与“火纹”。“凤凰”是中国古代传说中的神鸟，常用来象征祥瑞，火纹是中国古代先人在生活中物质与精神相互交融的产物，蕴含着旺盛的生命力。关注公众号人才考试",
          "OptionD" : "D.火麒麟",
          "OptionC" : "C.火纹"
        },
        {
          "OptionB" : "B.延庆赛区承办所有的雪上项目",
          "OptionA" : "A.2022年北京冬季奥运会共设8个大项",
          "TopicContent" : "17.2022年北京冬季奥运会于2022年2月4日开幕。关于北京冬奥会，下列表述错误的是(",
          "AnswerArr" : [
            "A",
            "B",
            "C"
          ],
          "IsMultipleChoice" : true,
          "AnswerContent" : "[答案] ABC。A项错误，2022 年北京冬季奥运会共设7个大项，15个分项，109个小项。B项错误，北京赛区承办所有的冰上项目，延庆赛区承办雪车、雪橇及高山滑雪项目，张家口赛区承办除雪车、雪橇及高山滑雪之外的所有雪上项且。C项错误，冰墩墩，是2022年北京冬季奥运会的吉祥物。将熊猫形象与富有超能量的冰晶外壳相结合，头部外壳造型取自冰雪运动头盔，装饰彩色光环，整体形象酷似航天员。D项正确，2022 北京冬奥会会徽名为冬梦，以汉字“冬”为灵感来源，主色调为蓝色。关注公众号人才考试",
          "OptionD" : "D.北京2022年冬奧会会徽名为冬梦，主色调为蓝色",
          "OptionC" : "C.冰墩墩是2022年北京冬残奥会的吉祥物，将熊猫形象与富有超能量的冰晶外壳相结合"
        },
        {
          "OptionB" : "B.人民币现金",
          "OptionA" : "A.美元",
          "TopicContent" : "18.北京冬奧会期间，所有比赛和非比赛场地支付方式仅限于()等。",
          "AnswerArr" : [
            "B",
            "C",
            "D"
          ],
          "IsMultipleChoice" : true,
          "AnswerContent" : "[答案] BCD。奥运会期间，所有比赛和非比赛场地只接受人民币现金、威士卡和数字人民币。注:威士卡(VISA) 又译为维萨、维信，是一个信用卡品牌，连接着全世界200多个国家和地区的消费者、企业、金融机构和政府，促进人们更方便地使用数字货币，代替现金或支票。关注公众号人才考试",
          "OptionD" : "D.数字人民币",
          "OptionC" : "C.威士卡"
        },
        {
          "OptionB" : "B.唐花飞雪",
          "OptionA" : "A.瑞雪祥云",
          "TopicContent" : "19.2021年1月，北京2022年冬奥会和冬残奥会颁奖礼仪服装发布，包括",
          "AnswerArr" : [
            "A",
            "B",
            "C"
          ],
          "IsMultipleChoice" : true,
          "AnswerContent" : "[答案]ABC。2021年1月，北京2022年冬奥会和冬残奥会颁奖礼仪服装发布一共有三套方案，分别为“瑞雪祥云”、“鸿运山水” 和“唐花飞雪”，设计灵感来自“瑞雪”、“祥云”、名画《千里江山图》、传统唐代织物等中国传统文化元素。关注公众号人才考试",
          "OptionD" : "D.马踏飞燕",
          "OptionC" : "C.鸿运山水"
        },
        {
          "OptionB" : "B.团结",
          "OptionA" : "A.和平",
          "TopicContent" : "20.“一起向未来”是中国向世界发出的诚挚邀约，传递出14亿中国人民的美好期待，更是行动方案，倡导追求( ) 的共同目标。",
          "AnswerArr" : [
            "A",
            "B",
            "C",
            "D"
          ],
          "IsMultipleChoice" : true,
          "AnswerContent" : "[答案] ABCD。“- 起向未来”是态度、是倡议、更是行动方案，倡导追求团结、和平、进步、包容的共同目标，是更快、更高、更强、更团结奥林匹克精神的中国宣扬，表达了世界需要携手走向美好未来的共同愿望。",
          "OptionD" : "D.包容",
          "OptionC" : "C.进步"
        }
      ]
    }
  ]
}